wpasupplicantconf.py
wpasupplicantconf-0.1.dist-info/METADATA
wpasupplicantconf-0.1.dist-info/RECORD
wpasupplicantconf-0.1.dist-info/WHEEL
wpasupplicantconf-0.1.dist-info/top_level.txt
