Metadata-Version: 2.1
Name: wpasupplicantconf
Version: 0.1
Summary: Parsing, manipulation and generation of wpa_supplicant.conf files
Home-page: https://github.com/TheCacophonyProject/wpasupplicantconf
Author: Menno Finlay-Smits
Author-email: menno@cacophony.org.nz
License: UNKNOWN
Platform: UNKNOWN
Classifier: Development Status :: 4 - Beta
Classifier: Intended Audience :: Developers
Classifier: Intended Audience :: System Administrators
